fenda/settings/__init__.py
fenda_settings-0.0.2.dist-info/METADATA
fenda_settings-0.0.2.dist-info/WHEEL
fenda_settings-0.0.2.dist-info/top_level.txt
fenda_settings-0.0.2.dist-info/RECORD
